jgraph/__init__.py
jgraph/force_directed_layout.py
jgraph/json_formatter.py
jgraph/notebook.py
jgraph/js/build/jgraph.min.js
jgraph-0.2.1.dist-info/DESCRIPTION.rst
jgraph-0.2.1.dist-info/METADATA
jgraph-0.2.1.dist-info/RECORD
jgraph-0.2.1.dist-info/WHEEL
jgraph-0.2.1.dist-info/metadata.json
jgraph-0.2.1.dist-info/top_level.txt
